MANIFEST.in
README.md
setup.py
lambda_pyskel/__init__.py
lambda_pyskel.egg-info/PKG-INFO
lambda_pyskel.egg-info/SOURCES.txt
lambda_pyskel.egg-info/dependency_links.txt
lambda_pyskel.egg-info/entry_points.txt
lambda_pyskel.egg-info/not-zip-safe
lambda_pyskel.egg-info/requires.txt
lambda_pyskel.egg-info/top_level.txt
lambda_pyskel/scripts/__init__.py
lambda_pyskel/scripts/cli.py
lambda_pyskel/templates/gdal/Dockerfile
lambda_pyskel/templates/gdal/Makefile
lambda_pyskel/templates/gdal/README.md
lambda_pyskel/templates/gdal/setup.py
lambda_pyskel/templates/gdal/tox.ini
lambda_pyskel/templates/gdal/pyskel/__init__.py
lambda_pyskel/templates/gdal/pyskel/handler.py
lambda_pyskel/templates/gdal/tests/test_handler.py
lambda_pyskel/templates/gdal/tests/test_mod.py
lambda_pyskel/templates/rasterio/Dockerfile
lambda_pyskel/templates/rasterio/Makefile
lambda_pyskel/templates/rasterio/README.md
lambda_pyskel/templates/rasterio/setup.py
lambda_pyskel/templates/rasterio/tox.ini
lambda_pyskel/templates/rasterio/pyskel/__init__.py
lambda_pyskel/templates/rasterio/pyskel/handler.py
lambda_pyskel/templates/rasterio/tests/test_handler.py
lambda_pyskel/templates/rasterio/tests/test_mod.py
lambda_pyskel/templates/simple/Dockerfile
lambda_pyskel/templates/simple/Makefile
lambda_pyskel/templates/simple/README.md
lambda_pyskel/templates/simple/setup.py
lambda_pyskel/templates/simple/tox.ini
lambda_pyskel/templates/simple/pyskel/__init__.py
lambda_pyskel/templates/simple/pyskel/handler.py
lambda_pyskel/templates/simple/tests/test_handler.py
lambda_pyskel/templates/simple/tests/test_mod.py
lambda_pyskel/templates/toolkits/kes/package.json
lambda_pyskel/templates/toolkits/kes/.kes/cloudformation.template.yml
lambda_pyskel/templates/toolkits/kes/.kes/config.yml
lambda_pyskel/templates/toolkits/serverless/package.json
lambda_pyskel/templates/toolkits/serverless/serverless.yml