Metadata-Version: 2.1
Name: lambda-pyskel
Version: 3.0.0
Summary: Create skeleton of a python AWS Lambda function
Home-page: https://github.com/vincentsarago/lambda-pyskel
Author: Vincent Sarago
Author-email: vincent.sarago@gmail.com
License: BSD-3
Keywords: AWS-Lambda Python
Platform: UNKNOWN
Classifier: Intended Audience :: Information Technology
Classifier: Intended Audience :: Science/Research
Classifier: License :: OSI Approved :: BSD License
Classifier: Programming Language :: Python :: 3.6
Classifier: Programming Language :: Python :: 3.7
Requires-Python: >=3
Provides-Extra: test
Provides-Extra: dev
